{
    "depressed": 0,
    "words": 22,
    "sentences": 2,
    "statements": 1,
    "clauses": 4,
    "sentece_length_data": {
        "avg": 11.0,
        "median": 11.0,
        "interquartile": 3.0
    },
    "clauses_data": {
        "avg": 2.0,
        "median": 2.0,
        "interquartile": 0.0
    },
    "lexsophistication_data": {
        "avg": 5.0,
        "median": 5.0,
        "interquartile": 2.0
    },
    "sentece_unique_words_data": {
        "avg": 9.5,
        "median": 9.5,
        "interquartile": 1.5
    },
    "unique_words": {
        "count": 17,
        "percentage": 0.7727
    },
    "language": {
        "sentiment": {
            "statement": {
                "positive": {
                    "count": 0,
                    "percentage": 0.0
                },
                "negative": {
                    "count": 1,
                    "percentage": 1.0
                },
                "neutral": {
                    "count": 0,
                    "percentage": 0.0
                }
            },
            "sentence": {
                "positive": {
                    "count": 0,
                    "percentage": 0.0
                },
                "negative": {
                    "count": 0,
                    "percentage": 0.0
                },
                "neutral": {
                    "count": 2,
                    "percentage": 1.0
                }
            },
            "word": {
                "positive": {
                    "count": 0,
                    "percentage": 0.0
                },
                "negative": {
                    "count": 3,
                    "percentage": 0.1364
                },
                "neutral": {
                    "count": 19,
                    "percentage": 0.8636
                }
            }
        },
        "clasuses_per_statement": {
            "avg": [
                2.0
            ],
            "map": [
                [
                    2,
                    2
                ]
            ],
            "median": [
                2.0
            ],
            "interquartile": [
                0.0
            ]
        },
        "lexialspohistication_per_statement": {
            "avg": [
                5.0
            ],
            "map": [
                [
                    7,
                    3
                ]
            ],
            "median": [
                5.0
            ],
            "interquartile": [
                2.0
            ],
            "mapdetail": [
                [
                    {
                        "count": 7,
                        "percent": 0.5,
                        "lengths": [
                            4,
                            8,
                            7,
                            9,
                            7,
                            7,
                            4,
                            7,
                            5,
                            3
                        ]
                    },
                    {
                        "count": 3,
                        "percent": 0.375,
                        "lengths": [
                            4,
                            8,
                            7,
                            9,
                            7,
                            7,
                            4,
                            7,
                            5,
                            3
                        ]
                    }
                ]
            ]
        },
        "lexial_density_per_sentece": [
            [
                {
                    "wps": 14,
                    "typesmap": [
                        "VERB|Tense=Past|VerbForm=Part",
                        "PRON|Case=Acc|Number=Sing|Person=1|PronType=Prs|Reflex=Yes",
                        "VERB|Mood=Ind|Number=Sing|Person=2|Tense=Pres|VerbForm=Fin",
                        "ADP|",
                        "ADV|",
                        "VERB|VerbForm=Inf",
                        "AUX|Mood=Ind|Number=Sing|Person=2|Tense=Pres|VerbForm=Fin",
                        "NOUN|Number=Sing",
                        "PRON|Case=Nom|Person=2|PronType=Prs",
                        "NOUN|Number=Plur",
                        "ADJ|Degree=Pos"
                    ],
                    "value": 0.7857,
                    "text": "you*ever*have*thoughts*about*suicide*have*you*attempted*suicide*just*picture*myself*dead*"
                },
                {
                    "wps": 8,
                    "typesmap": [
                        "PRON|Case=Nom|Gender=Neut|Number=Sing|Person=3|PronType=Prs",
                        "PRON|Person=2|Poss=Yes|PronType=Prs",
                        "VERB|Mood=Ind|Number=Sing|Person=2|Tense=Pres|VerbForm=Fin",
                        "SCONJ|PronType=Int",
                        "NOUN|Number=Sing",
                        "AUX|Mood=Ind|Number=Sing|Person=3|Tense=Pres|VerbForm=Fin",
                        "PRON|Case=Nom|Person=2|PronType=Prs",
                        "ADV|PronType=Int"
                    ],
                    "value": 1.0,
                    "text": "When*you*picture*your*death*how*is*it*"
                }
            ]
        ],
        "lexial_density_per_sentece_nofeats": [
            [
                {
                    "wps": 14,
                    "typesmap": [
                        "PRON",
                        "AUX",
                        "NOUN",
                        "ADJ",
                        "VERB",
                        "ADP",
                        "ADV"
                    ],
                    "value": 0.5
                },
                {
                    "wps": 8,
                    "typesmap": [
                        "PRON",
                        "AUX",
                        "NOUN",
                        "SCONJ",
                        "VERB",
                        "ADV"
                    ],
                    "value": 0.75
                }
            ]
        ],
        "sentece_length": {
            "avg": [
                11.0
            ],
            "map": [
                [
                    14,
                    8
                ]
            ],
            "median": [
                11.0
            ],
            "interquartile": [
                3.0
            ]
        },
        "sentece_unique_words": {
            "avg": [
                9.5
            ],
            "map": [
                [
                    11,
                    8
                ]
            ],
            "median": [
                9.5
            ],
            "interquartile": [
                1.5
            ]
        },
        "pronoun_fps": {
            "count": 1,
            "percentage": 0.0455
        },
        "absolutist_words_small": {
            "count": 0,
            "percentage": 0.0
        },
        "absolutist_words_full": {
            "count": 1,
            "percentage": 0.0455
        },
        "depression_specific_words": {
            "count": 0,
            "percentage": 0.0
        },
        "pastwords": {
            "count": 1,
            "percentage": 0.0455
        }
    },
    "avg_lexdensity_per_specific_POS": 0.4545,
    "avg_lexdensity_senetece": 0.8928,
    "avg_lexdensity_senetece_nofeats": 0.625,
    "avg_lexdensity_video": 0.7272727272727273,
    "avg_lexdensity_video_nofeats": 0.36363636363636365,
    "avg_lexdensity_video_normalized": 0.16,
    "avg_lexdensity_video_nofeats_normalized": 0.08
}